nosodata_py/__init__.py
nosodata_py/block.py
nosodata_py/pascal.py
nosodata_py/streams.py
nosodata_py-0.1.3.dist-info/LICENSE
nosodata_py-0.1.3.dist-info/METADATA
nosodata_py-0.1.3.dist-info/WHEEL
nosodata_py-0.1.3.dist-info/top_level.txt
nosodata_py-0.1.3.dist-info/RECORD
