Metadata-Version: 2.1
Name: nosodata_py
Version: 0.1.3
Summary: Set of classes to read the data from Noso files
Home-page: https://github.com/Friends-Of-Noso/NosoData-Py
Author: Gustavo 'Gus' Carreno
Author-email: guscarreno@gmail.com
License: MIT
License-File: LICENSE
